cactus_test_definitions/__init__.py
cactus_test_definitions/csipaus.py
cactus_test_definitions/errors.py
cactus_test_definitions/parameters.py
cactus_test_definitions/py.typed
cactus_test_definitions/schema.py
cactus_test_definitions/variable_expressions.py
cactus_test_definitions/__pycache__/__init__.cpython-311.pyc
cactus_test_definitions/__pycache__/__init__.cpython-312.pyc
cactus_test_definitions/__pycache__/csipaus.cpython-311.pyc
cactus_test_definitions/__pycache__/csipaus.cpython-312.pyc
cactus_test_definitions/__pycache__/errors.cpython-311.pyc
cactus_test_definitions/__pycache__/errors.cpython-312.pyc
cactus_test_definitions/__pycache__/parameters.cpython-311.pyc
cactus_test_definitions/__pycache__/parameters.cpython-312.pyc
cactus_test_definitions/__pycache__/schema.cpython-312.pyc
cactus_test_definitions/__pycache__/variable_expressions.cpython-311.pyc
cactus_test_definitions/__pycache__/variable_expressions.cpython-312.pyc
cactus_test_definitions/client/__init__.py
cactus_test_definitions/client/actions.py
cactus_test_definitions/client/checks.py
cactus_test_definitions/client/events.py
cactus_test_definitions/client/test_procedures.py
cactus_test_definitions/client/validate.py
cactus_test_definitions/client/__pycache__/__init__.cpython-311.pyc
cactus_test_definitions/client/__pycache__/__init__.cpython-312.pyc
cactus_test_definitions/client/__pycache__/actions.cpython-311.pyc
cactus_test_definitions/client/__pycache__/actions.cpython-312.pyc
cactus_test_definitions/client/__pycache__/checks.cpython-311.pyc
cactus_test_definitions/client/__pycache__/checks.cpython-312.pyc
cactus_test_definitions/client/__pycache__/events.cpython-311.pyc
cactus_test_definitions/client/__pycache__/events.cpython-312.pyc
cactus_test_definitions/client/__pycache__/test_procedures.cpython-311-pytest-8.3.3.pyc
cactus_test_definitions/client/__pycache__/test_procedures.cpython-312-pytest-8.3.4.pyc
cactus_test_definitions-1.8.13.dist-info/licenses/LICENSE.txt
cactus_test_definitions-1.8.13.dist-info/METADATA
cactus_test_definitions-1.8.13.dist-info/WHEEL
cactus_test_definitions-1.8.13.dist-info/top_level.txt
cactus_test_definitions-1.8.13.dist-info/RECORD
