Metadata-Version: 2.4
Name: cactus-test-definitions
Version: 1.8.13
Summary: CSIP-AUS Client Test Harness Test Definitions
Author-email: Mike Turner <mike.turner@anu.edu.au>, Josh Vote <joshua.vote@anu.edu.au>
Maintainer-email: Mike Turner <mike.turner@anu.edu.au>, Josh Vote <joshua.vote@anu.edu.au>
Project-URL: Homepage, https://github.com/bsgip/cactus-test-definitions
Project-URL: Documentation, https://github.com/bsgip/cactus-test-definitions/blob/main/README.md
Project-URL: Repository, https://github.com/bsgip/cactus-test-definitions.git
Project-URL: Issues, https://github.com/bsgip/cactus-test-definitions/issues
Project-URL: Changelog, https://github.com/bsgip/cactus-test-definitions/blob/main/CHANGELOG.md
Keywords: CSIP-AUS,client,testing,definitions
Classifier: Development Status :: 3 - Alpha
Classifier: Environment :: Console
Classifier: Intended Audience :: Developers
Classifier: Operating System :: OS Independent
Classifier: Programming Language :: Python :: 3.12
Classifier: Topic :: Software Development
Classifier: Typing :: Typed
Requires-Python: >=3.12
License-File: LICENSE.txt
Requires-Dist: pyyaml<7,>=6.0.2
Requires-Dist: pyyaml-include<3,>=2.2
Requires-Dist: dataclass-wizard<1,==0.35.0
Provides-Extra: dev
Requires-Dist: bandit; extra == "dev"
Requires-Dist: black; extra == "dev"
Requires-Dist: flake8; extra == "dev"
Requires-Dist: isort; extra == "dev"
Requires-Dist: mccabe; extra == "dev"
Requires-Dist: mypy; extra == "dev"
Requires-Dist: tox; extra == "dev"
Requires-Dist: python-dotenv[cli]; extra == "dev"
Requires-Dist: types-PyYAML; extra == "dev"
Provides-Extra: test
Requires-Dist: pytest; extra == "test"
Requires-Dist: assertical; extra == "test"
Provides-Extra: docs
Requires-Dist: sphinx; extra == "docs"
Dynamic: license-file
